sappy/__init__.py
sappy/__main__.py
sappy/cli.py
sappy/handlers.py
sappy/server.py
sappy/settings.py
sappy/tests/__init__.py
sappy/tests/conftest.py
sappy/tests/test_settings.py
sappy-1.2.dist-info/LICENSE.md
sappy-1.2.dist-info/METADATA
sappy-1.2.dist-info/WHEEL
sappy-1.2.dist-info/entry_points.txt
sappy-1.2.dist-info/RECORD
