Metadata-Version: 2.1
Name: sappy
Version: 1.2
Summary: Single-page application server for end-to-end testing.
Home-page: https://pypi.org/project/sappy
License: MIT
Keywords: testing,end-to-end,single-page-application,web-servicer
Author: Jace Browning
Author-email: jacebrowning@gmail.com
Requires-Python: >=3.8,<4.0
Classifier: Development Status :: 5 - Production/Stable
Classifier: Environment :: Console
Classifier: Intended Audience :: Developers
Classifier: License :: OSI Approved :: MIT License
Classifier: Natural Language :: English
Classifier: Operating System :: OS Independent
Classifier: Programming Language :: Python
Classifier: Programming Language :: Python :: 3
Classifier: Programming Language :: Python :: 3.8
Classifier: Programming Language :: Python :: 3.9
Classifier: Programming Language :: Python :: 3.10
Classifier: Programming Language :: Python :: 3.11
Classifier: Topic :: Software Development
Classifier: Topic :: Software Development :: Testing
Requires-Dist: click (>=8.0,<9.0)
Requires-Dist: minilog (>=2.0,<3.0)
Project-URL: Documentation, https://sappy.readthedocs.io
Project-URL: Repository, https://github.com/jacebrowning/sappy
